sequel/__init__.py
sequel/__main__.py
sequel/app.py
sequel/cli.py
sequel/commands.py
sequel/config.py
sequel/config_file.py
sequel/cache/__init__.py
sequel/cache/memory.py
sequel/models/__init__.py
sequel/models/base.py
sequel/models/clouddns.py
sequel/models/cloudsql.py
sequel/models/compute.py
sequel/models/firewall.py
sequel/models/gke.py
sequel/models/iam.py
sequel/models/monitoring.py
sequel/models/networks.py
sequel/models/project.py
sequel/models/pubsub.py
sequel/models/secrets.py
sequel/models/storage.py
sequel/screens/__init__.py
sequel/screens/main.py
sequel/services/__init__.py
sequel/services/auth.py
sequel/services/base.py
sequel/services/clouddns.py
sequel/services/cloudsql.py
sequel/services/compute.py
sequel/services/firewall.py
sequel/services/gke.py
sequel/services/iam.py
sequel/services/monitoring.py
sequel/services/networks.py
sequel/services/projects.py
sequel/services/pubsub.py
sequel/services/secrets.py
sequel/services/storage.py
sequel/state/__init__.py
sequel/state/resource_state.py
sequel/utils/__init__.py
sequel/utils/logging.py
sequel/utils/regex_validator.py
sequel/widgets/__init__.py
sequel/widgets/detail_pane.py
sequel/widgets/error_modal.py
sequel/widgets/loading_indicator.py
sequel/widgets/resource_tree.py
sequel/widgets/status_bar.py
sequel_ag-1.6.1.dist-info/licenses/LICENSE
sequel_ag-1.6.1.dist-info/METADATA
sequel_ag-1.6.1.dist-info/WHEEL
sequel_ag-1.6.1.dist-info/entry_points.txt
sequel_ag-1.6.1.dist-info/top_level.txt
sequel_ag-1.6.1.dist-info/RECORD
