Metadata-Version: 2.4
Name: sequel-ag
Version: 1.6.1
Summary: A TUI for browsing Google Cloud resources
Author: Sequel Contributors
License: MIT
Classifier: Development Status :: 3 - Alpha
Classifier: Intended Audience :: Developers
Classifier: Topic :: System :: Systems Administration
Classifier: License :: OSI Approved :: MIT License
Classifier: Programming Language :: Python :: 3
Classifier: Programming Language :: Python :: 3.11
Classifier: Programming Language :: Python :: 3.12
Requires-Python: >=3.11
License-File: LICENSE
Requires-Dist: textual>=0.47.0
Requires-Dist: tree-sitter>=0.21.0
Requires-Dist: tree-sitter-languages>=1.10.0
Requires-Dist: tree-sitter-json>=0.24.0
Requires-Dist: google-auth>=2.25.0
Requires-Dist: google-auth-oauthlib>=1.2.0
Requires-Dist: google-api-python-client>=2.110.0
Requires-Dist: google-api-python-client-stubs>=1.31.0
Requires-Dist: google-cloud-resource-manager>=1.12.0
Requires-Dist: google-cloud-container>=2.36.0
Requires-Dist: google-cloud-secret-manager>=2.18.0
Requires-Dist: pydantic>=2.5.0
Requires-Dist: aiohttp>=3.9.0
Requires-Dist: pyperclip>=1.8.0
Dynamic: license-file
